{"name":"bigdata","slug":"bigdata","count":2,"postlist":[{"title":"大数据相关的一些名词","uid":"abbd863cb849430f5ba6ae97c8807bd7","slug":"大数据相关的一些名词","date":"2022-09-09T16:36:11.000Z","updated":"2023-05-11T06:03:44.625Z","comments":true,"path":"api/articles/大数据相关的一些名词.json","keywords":null,"cover":[],"text":" 据仓库(data warehouse) 也可以简称为 DW DH 数据仓库中的分层:1. 数据运营层 ODS ODS(Operation Data Store): 数据准备区,最接近数据源的一层, 也称为 贴源层. 数据仓库中 源头系统的数据通常会原封不动的存储一份. 这称为为...","link":"","photos":[],"count_time":{"symbolsCount":"1.6k","symbolsTime":"1 mins."},"categories":[{"name":"bigdata","slug":"bigdata","count":2,"path":"api/categories/bigdata.json"}],"tags":[{"name":"bigdata","slug":"bigdata","count":2,"path":"api/tags/bigdata.json"}],"author":{"name":"majm","slug":"blog-author","avatar":"https://img-blog.csdnimg.cn/20210313122054101.png","link":"/","description":"技术分享","socials":{"github":"","twitter":"","stackoverflow":"","wechat":"","qq":"","weibo":"","zhihu":"","csdn":"","juejin":"","customs":{}}}},{"title":"大数据-数据仓库大宽表","uid":"7b7fae18844a9a83dfd9701a806d24e8","slug":"大数据-数据仓库大宽表","date":"2023-03-01T13:17:02.000Z","updated":"2023-03-01T15:59:43.086Z","comments":true,"path":"api/articles/大数据-数据仓库大宽表.json","keywords":null,"cover":null,"text":"什么是大宽表, 为什么要使用大宽表, 大宽表有什么优缺点, 设计大宽表要注意什么? 参考一起聊聊数仓大宽表 ","link":"","photos":[],"count_time":{"symbolsCount":62,"symbolsTime":"1 mins."},"categories":[{"name":"bigdata","slug":"bigdata","count":2,"path":"api/categories/bigdata.json"}],"tags":[{"name":"bigdata","slug":"bigdata","count":2,"path":"api/tags/bigdata.json"}],"author":{"name":"majm","slug":"blog-author","avatar":"https://img-blog.csdnimg.cn/20210313122054101.png","link":"/","description":"技术分享","socials":{"github":"","twitter":"","stackoverflow":"","wechat":"","qq":"","weibo":"","zhihu":"","csdn":"","juejin":"","customs":{}}},"feature":true}]}