{"name":"blog","slug":"blog","count":3,"postlist":[{"title":"awesome-blog","uid":"237d42f01cd872e0a7556a026d085cc6","slug":"awesome-blog","date":"2022-08-16T12:45:48.000Z","updated":"2022-09-08T05:02:48.272Z","comments":true,"path":"api/articles/awesome-blog.json","keywords":null,"cover":null,"text":"golang极客兔兔跟煎鱼学GoO神的博客曹大的博客 Java小马哥的技术博客田小波的技术博客 Architechcleancoders解道凤凰架构 LinuxFRIMIN鸟哥的首页Vamei 算法谭新宇LABULADONG 的算法网站结构之法算法之道kuangbin - 博客园...","link":"","photos":[],"count_time":{"symbolsCount":348,"symbolsTime":"1 mins."},"categories":[],"tags":[{"name":"blog","slug":"blog","count":3,"path":"api/tags/blog.json"}],"author":{"name":"majm","slug":"blog-author","avatar":"https://img-blog.csdnimg.cn/20210313122054101.png","link":"/","description":"技术分享","socials":{"github":"","twitter":"","stackoverflow":"","wechat":"","qq":"","weibo":"","zhihu":"","csdn":"","juejin":"","customs":{}}}},{"title":"hexo中插入图片","uid":"ffad35a1622d678553fcb007d75f9511","slug":"hexo中插入图片","date":"2022-03-03T15:52:29.000Z","updated":"2022-03-03T16:35:40.358Z","comments":true,"path":"api/articles/hexo中插入图片.json","keywords":null,"cover":null,"text":"在 hexo 中使用 图片, 有如下几种方式: 1. 在 资源目录下 创建图片 hexo 配置文件 _config.yml post_asset_folder: true # 创建新文章时，会生成相同名字的文件夹，也就是文章资源文件夹 当执行命令 hexo new &quot;t...","link":"","photos":[],"count_time":{"symbolsCount":516,"symbolsTime":"1 mins."},"categories":[{"name":"hexo","slug":"hexo","count":2,"path":"api/categories/hexo.json"}],"tags":[{"name":"blog","slug":"blog","count":3,"path":"api/tags/blog.json"},{"name":"image","slug":"image","count":1,"path":"api/tags/image.json"}],"author":{"name":"majm","slug":"blog-author","avatar":"https://img-blog.csdnimg.cn/20210313122054101.png","link":"/","description":"技术分享","socials":{"github":"","twitter":"","stackoverflow":"","wechat":"","qq":"","weibo":"","zhihu":"","csdn":"","juejin":"","customs":{}}}},{"title":"升级hexo-cli的版本","uid":"33a93209a96a0749f2f19c4e853409bf","slug":"升级hexo-cli的版本","date":"2022-03-03T15:26:10.000Z","updated":"2022-03-03T15:48:46.861Z","comments":true,"path":"api/articles/升级hexo-cli的版本.json","keywords":null,"cover":[],"text":"最近升级 node版本后,执行 hexo d 就会报错: NFO Copying files from public folder... FATAL &#123; err: TypeError [ERR_INVALID_ARG_TYPE]: The &quot;mode&quot...","link":"","photos":[],"count_time":{"symbolsCount":796,"symbolsTime":"1 mins."},"categories":[{"name":"hexo","slug":"hexo","count":2,"path":"api/categories/hexo.json"}],"tags":[{"name":"blog","slug":"blog","count":3,"path":"api/tags/blog.json"},{"name":"hexo","slug":"hexo","count":1,"path":"api/tags/hexo.json"}],"author":{"name":"majm","slug":"blog-author","avatar":"https://img-blog.csdnimg.cn/20210313122054101.png","link":"/","description":"技术分享","socials":{"github":"","twitter":"","stackoverflow":"","wechat":"","qq":"","weibo":"","zhihu":"","csdn":"","juejin":"","customs":{}}}}]}